credit_scoring/__init__.py
credit_scoring/credit_scoring.py
multilayer_credit_scoring-0.0.7.dist-info/LICENSE
multilayer_credit_scoring-0.0.7.dist-info/METADATA
multilayer_credit_scoring-0.0.7.dist-info/WHEEL
multilayer_credit_scoring-0.0.7.dist-info/dependency_links.txt
multilayer_credit_scoring-0.0.7.dist-info/top_level.txt
multilayer_credit_scoring-0.0.7.dist-info/RECORD
