Metadata-Version: 2.1
Name: multilayer-credit-scoring
Version: 0.0.7
Summary: Python implementation of the MultilayerCreditScoring algorithm
Home-page: https://github.com/MariaOskarsdottir/MultilayerCreditScoring
Author: Sigurjon Thorsteinsson
Author-email: grjoni80@gmail.com
License: UNKNOWN
Platform: UNKNOWN
Classifier: Programming Language :: Python :: 3.8
Classifier: License :: OSI Approved :: GNU General Public License v3 (GPLv3)
Classifier: Operating System :: OS Independent
Requires-Python: >=3.8
Requires-Dist: numpy (==1.19)
Requires-Dist: networkx (==2.3)
Requires-Dist: scipy (==1.5)
Requires-Dist: scikit-learn (==0.23)
